mv_components/ActiveComponent.py
mv_components/Exceptions.py
mv_components/MVComponentProvider.py
mv_components/__init__.py
mv_components/mv_component_ext.py
mv_components/stubs/component.stub
mv_components/stubs/mv_component.stub
mv_components-0.2.7.dist-info/LICENSE
mv_components-0.2.7.dist-info/METADATA
mv_components-0.2.7.dist-info/WHEEL
mv_components-0.2.7.dist-info/top_level.txt
mv_components-0.2.7.dist-info/RECORD
