Metadata-Version: 2.1
Name: mv-components
Version: 0.2.7
Summary: A framework to create reusable server rendered components with low coupling and easy testability.
Home-page: https://github.com/JarriqTheTechie/mv-component
Author: Jarriq Rolle
Author-email: jrolle@bnbbahamas.com
License: MIT license
Keywords: Masonite,Python,Development,Flask
Classifier: Development Status :: 5 - Production/Stable
Classifier: Intended Audience :: Developers
Classifier: Environment :: Web Environment
Classifier: License :: OSI Approved :: MIT License
Classifier: Operating System :: OS Independent
Classifier: Programming Language :: Python :: 3.6
Classifier: Programming Language :: Python :: 3.7
Classifier: Programming Language :: Python :: 3.8
Classifier: Programming Language :: Python :: 3.9
Classifier: Topic :: Software Development :: Libraries :: Application Frameworks
Classifier: Topic :: Software Development :: Libraries :: Python Modules
Classifier: Framework :: Masonite
License-File: LICENSE
Provides-Extra: flask
Requires-Dist: flask ; extra == 'flask'
Provides-Extra: masonite
Requires-Dist: masonite ; extra == 'masonite'
